django_socketio_chat/__init__.py
django_socketio_chat/adapter.py
django_socketio_chat/migrations/0001_initial.py
django_socketio_chat/migrations/__init__.py
django_socketio_chat/models.py
django_socketio_chat/server.py
django_socketio_chat/static/django_socketio_chat/css/main.css
django_socketio_chat/static/django_socketio_chat/js/letter_avatar.js
django_socketio_chat/templates/django_socketio_chat/index.html
django_socketio_chat/urls.py
django_socketio_chat/views.py
django_socketio_chat-0.1.1.dist-info/METADATA
django_socketio_chat-0.1.1.dist-info/WHEEL
django_socketio_chat-0.1.1.dist-info/RECORD
