Metadata-Version: 2.1
Name: django-socketio-chat
Version: 0.1.1
Summary: Django SocketIO Chat using python-socketio
Home-page: https://github.com/ThuanD/django-socketio-chat/
Author: kai
Author-email: thuan.dv0@gmail.com
Requires-Python: >=3.10,<4.0
Classifier: Programming Language :: Python :: 3
Classifier: Programming Language :: Python :: 3.10
Classifier: Programming Language :: Python :: 3.11
Classifier: Programming Language :: Python :: 3.12
Requires-Dist: django-allauth-simple-ui (>=0.1.2,<0.2.0)
Requires-Dist: djangorestframework-simplejwt (>=5.3.1,<6.0.0)
Requires-Dist: eventlet (>=0.37.0,<0.38.0)
Requires-Dist: gunicorn (>=23.0.0,<24.0.0)
Requires-Dist: python-socketio (>=5.11.4,<6.0.0)
Project-URL: Repository, https://github.com/ThuanD/django-socketio-chat/
